[
 {
   "round": "3/2562",
   "citizen_id": "TH0000000601",
   "course_id": "C0033",
   "priority": 1
 },
 {
   "round": "3/2562",
   "citizen_id": "TH0000000602",
   "course_id": "C0033",
   "priority": 2
 },
 {
   "round": "3/2562",
   "citizen_id": "TH0000000603",
   "course_id": "C0033",
   "priority": 3
 },
 {
   "round": "3/2562",
   "citizen_id": "TH0000000604",
   "course_id": "C0034",
   "priority": 1
 },
 {
   "round": "3/2562",
   "citizen_id": "TH0000000605",
   "course_id": "C0034",
   "priority": 1
 },
 {
   "round": "3/2562",
   "citizen_id": "TH0000000606",
   "course_id": "C0035",
   "priority": 1
 },
 {
   "round": "3/2562",
   "citizen_id": "TH0000000607",
   "course_id": "C0035",
   "priority": 2
 },
 {
   "round": "3/2562",
   "citizen_id": "TH0000000608",
   "course_id": "C0035",
   "priority": 3
 },
 {
   "round": "3/2562",
   "citizen_id": "TH0000000609",
   "course_id": "C0036",
   "priority": 1
 },
 {
   "round": "3/2562",
   "citizen_id": "TH0000000610",
   "course_id": "C0036",
   "priority": 1
 },
 {
   "round": "3/2562",
   "citizen_id": "TH0000000611",
   "course_id": "C0037",
   "priority": 1
 },
 {
   "round": "3/2562",
   "citizen_id": "TH0000000612",
   "course_id": "C0037",
   "priority": 2
 },
 {
   "round": "3/2562",
   "citizen_id": "TH0000000613",
   "course_id": "C0037",
   "priority": 3
 },
 {
   "round": "3/2562",
   "citizen_id": "TH0000000614",
   "course_id": "C0038",
   "priority": 1
 },
 {
   "round": "3/2562",
   "citizen_id": "TH0000000615",
   "course_id": "C0038",
   "priority": 1
 },
 {
   "round": "3/2562",
   "citizen_id": "TH0000000616",
   "course_id": "C0039",
   "priority": 1
 },
 {
   "round": "3/2562",
   "citizen_id": "TH0000000617",
   "course_id": "C0039",
   "priority": 2
 },
 {
   "round": "3/2562",
   "citizen_id": "TH0000000618",
   "course_id": "C0039",
   "priority": 3
 },
 {
   "round": "3/2562",
   "citizen_id": "TH0000000619",
   "course_id": "C0040",
   "priority": 1
 },
 {
   "round": "3/2562",
   "citizen_id": "TH0000000620",
   "course_id": "C0040",
   "priority": 1
 },
 {
   "round": "3/2562",
   "citizen_id": "TH0000000621",
   "course_id": "C0040",
   "priority": 4
 },
 {
   "round": "3/2562",
   "citizen_id": "TH0000000622",
   "course_id": "C0041",
   "priority": 1
 },
 {
   "round": "3/2562",
   "citizen_id": "TH0000000623",
   "course_id": "C0041",
   "priority": 1
 },
 {
   "round": "3/2562",
   "citizen_id": "TH0000000624",
   "course_id": "C0042",
   "priority": 1
 },
 {
   "round": "3/2562",
   "citizen_id": "TH0000000625",
   "course_id": "C0042",
   "priority": 2
 },
 {
   "round": "3/2562",
   "citizen_id": "TH0000000626",
   "course_id": "C0036",
   "priority": 3
 },
 {
   "round": "3/2562",
   "citizen_id": "TH0000000627",
   "course_id": "C0035",
   "priority": 1
 },
 {
   "round": "3/2562",
   "citizen_id": "TH0000000628",
   "course_id": "C0036",
   "priority": 1
 },
 {
   "round": "3/2562",
   "citizen_id": "TH0000000629",
   "course_id": "C0038",
   "priority": 1
 },
 {
   "round": "3/2562",
   "citizen_id": "TH0000000630",
   "course_id": "C0037",
   "priority": 2
 },
 {
   "round": "3/2562",
   "citizen_id": "TH0000000631",
   "course_id": "C0038",
   "priority": 3
 },
 {
   "round": "3/2562",
   "citizen_id": "TH0000000632",
   "course_id": "C0039",
   "priority": 1
 },
 {
   "round": "3/2562",
   "citizen_id": "TH0000000633",
   "course_id": "C0040",
   "priority": 1
 },
 {
   "round": "3/2562",
   "citizen_id": "TH0000000634",
   "course_id": "C0039",
   "priority": 2
 },
 {
   "round": "3/2562",
   "citizen_id": "TH0000000635",
   "course_id": "C0044",
   "priority": 5
 },
 {
   "round": "3/2562",
   "citizen_id": "TH0000000636",
   "course_id": "C0045",
   "priority": 6
 },
 {
   "round": "3/2562",
   "citizen_id": "TH0000000637",
   "course_id": "C0044",
   "priority": 1
 },
 {
   "round": "3/2562",
   "citizen_id": "TH0000000638",
   "course_id": "C0045",
   "priority": 1
 },
 {
   "round": "3/2562",
   "citizen_id": "TH0000000639",
   "course_id": "C0044",
   "priority": 1
 },
 {
   "round": "3/2562",
   "citizen_id": "TH0000000640",
   "course_id": "C0045",
   "priority": 1
 },
 {
   "round": "3/2562",
   "citizen_id": "TH0000000641",
   "course_id": "C0044",
   "priority": 2
 },
 {
   "round": "3/2562",
   "citizen_id": "TH0000000642",
   "course_id": "C0045",
   "priority": 3
 },
 {
   "round": "3/2562",
   "citizen_id": "TH0000000643",
   "course_id": "C0044",
   "priority": 1
 }
]